vcrpy_encrypt/__init__.py
vcrpy_encrypt/persister.py
vcrpy_encrypt-0.9.2.dist-info/LICENSE
vcrpy_encrypt-0.9.2.dist-info/METADATA
vcrpy_encrypt-0.9.2.dist-info/WHEEL
vcrpy_encrypt-0.9.2.dist-info/RECORD
