Metadata-Version: 2.1
Name: vcrpy-encrypt
Version: 0.9.2
Summary: Encrypt vcrpy cassettes so they can be safely kept under version control.
Home-page: https://github.com/CarloDePieri/vcrpy-encrypt
License: GPL-3.0-only
Keywords: python,vcr,vcrpy,encrypt
Author: Carlo De Pieri
Author-email: depieri.carlo@gmail.com
Requires-Python: >=3.8.1,<4.0.0
Classifier: Development Status :: 4 - Beta
Classifier: Environment :: Console
Classifier: Intended Audience :: Developers
Classifier: License :: OSI Approved :: GNU General Public License v3 (GPLv3)
Classifier: Programming Language :: Python :: 3
Classifier: Programming Language :: Python :: 3.9
Classifier: Programming Language :: Python :: 3.10
Classifier: Programming Language :: Python :: 3.11
Classifier: Programming Language :: Python :: 3.12
Classifier: Programming Language :: Python :: 3.8
Classifier: Topic :: Software Development :: Testing
Classifier: Topic :: Utilities
Requires-Dist: cryptography (>=42.0.3,<43.0.0)
Requires-Dist: vcrpy (>=6.0.1,<7.0.0)
Project-URL: Repository, https://github.com/CarloDePieri/vcrpy-encrypt
